<?xml version="1.0" encoding="utf-8" ?>
<dwsync>
<file name="index.html" server="webdesign4.georgianc.on.ca" local="129996614914712774" remote="129996849000000000" />
<file name="style.css" server="webdesign4.georgianc.on.ca" local="129996655724546963" remote="129996849000000000" />
<file name="company.html" server="webdesign4.georgianc.on.ca" local="129996615010388246" remote="129996848400000000" />
<file name="member.html" server="webdesign4.georgianc.on.ca" local="129996647216750345" remote="129996849000000000" />
<file name="product.html" server="webdesign4.georgianc.on.ca" local="129996618999626418" remote="129996849000000000" />
<file name="promotion.html" server="webdesign4.georgianc.on.ca" local="129996635415885374" remote="129996849000000000" />
<file name="purchase.html" server="webdesign4.georgianc.on.ca" local="129996658939240833" remote="129996849000000000" />
<file name="style1.css" server="webdesign4.georgianc.on.ca" local="129996658086032032" remote="129996849000000000" />
<file name="style2.css" server="webdesign4.georgianc.on.ca" local="129996664643697109" remote="129996849000000000" />
<file name="support.html" server="webdesign4.georgianc.on.ca" local="129996619218048911" remote="129996849000000000" />
</dwsync>